docs/source/conf.py
xicam/XPCS/__init__.py
xicam/XPCS/ingestors/__init__.py
xicam/XPCS/projectors/__init__.py
xicam/XPCS/projectors/nexus.py
xicam.XPCS-1.3.1.dist-info/LICENSE.md
xicam.XPCS-1.3.1.dist-info/METADATA
xicam.XPCS-1.3.1.dist-info/WHEEL
xicam.XPCS-1.3.1.dist-info/entry_points.txt
xicam.XPCS-1.3.1.dist-info/top_level.txt
xicam.XPCS-1.3.1.dist-info/RECORD
