Metadata-Version: 2.1
Name: xicam.XPCS
Version: 1.3.1
Summary: XPCS GUI interface
Home-page: UNKNOWN
Author: Ron Pandolfi
Author-email: ronpandolfi@lbl.gov
License: BSD
Platform: UNKNOWN
Classifier: Development Status :: 3 - Alpha
Classifier: Intended Audience :: Developers
Classifier: Intended Audience :: Science/Research
Classifier: Topic :: Scientific/Engineering :: Physics
Classifier: Programming Language :: Python :: 3
Requires-Dist: xicam
Requires-Dist: xicam.SAXS
Requires-Dist: sphinx
Requires-Dist: sphinx-rtd-theme
Requires-Dist: nose
Requires-Dist: coverage
Requires-Dist: pypi-publisher
Requires-Dist: scipy
Requires-Dist: scikit-image
Requires-Dist: event-model
Requires-Dist: scikit-beam
